MANIFEST.in
README.rst
setup.cfg
setup.py
ndg/__init__.py
ndg/saml/__init__.py
ndg/saml/common/__init__.py
ndg/saml/common/xml.py
ndg/saml/saml2/__init__.py
ndg/saml/saml2/core.py
ndg/saml/saml2/xacml_profile.py
ndg/saml/saml2/binding/__init__.py
ndg/saml/saml2/binding/soap/__init__.py
ndg/saml/saml2/binding/soap/client/__init__.py
ndg/saml/saml2/binding/soap/client/attributequery.py
ndg/saml/saml2/binding/soap/client/authzdecisionquery.py
ndg/saml/saml2/binding/soap/client/requestbase.py
ndg/saml/saml2/binding/soap/client/subjectquery.py
ndg/saml/saml2/binding/soap/client/xacmlauthzdecisionquery.py
ndg/saml/saml2/binding/soap/server/__init__.py
ndg/saml/saml2/binding/soap/server/wsgi/__init__.py
ndg/saml/saml2/binding/soap/server/wsgi/queryinterface.py
ndg/saml/test/__init__.py
ndg/saml/test/test_factory.py
ndg/saml/test/test_saml.py
ndg/saml/test/utils.py
ndg/saml/test/binding/__init__.py
ndg/saml/test/binding/soap/__init__.py
ndg/saml/test/binding/soap/test_attributeservice.py
ndg/saml/test/binding/soap/test_attributeservice_paster.py
ndg/saml/test/binding/soap/test_authzservice.py
ndg/saml/test/binding/soap/test_queryinterface.py
ndg/saml/test/binding/soap/test_queryresponseinterface.py
ndg/saml/test/xml/__init__.py
ndg/saml/test/xml/test_saml_core.py
ndg/saml/test/xml/test_xacml_profile.py
ndg/saml/utils/__init__.py
ndg/saml/utils/command_line_client.py
ndg/saml/utils/factory.py
ndg/saml/utils/m2crypto.py
ndg/saml/utils/pyopenssl.py
ndg/saml/utils/ssl_context.py
ndg/saml/xml/__init__.py
ndg/saml/xml/etree.py
ndg/saml/xml/etree_xacml_profile.py
ndg/soap/__init__.py
ndg/soap/client.py
ndg/soap/etree.py
ndg/soap/server/__init__.py
ndg/soap/server/wsgi/__init__.py
ndg/soap/server/wsgi/middleware.py
ndg/soap/server/wsgi/zsi.py
ndg/soap/test/__init__.py
ndg/soap/test/soap_server.py
ndg/soap/test/test_soap.py
ndg/soap/utils/__init__.py
ndg/soap/utils/configfileparsers.py
ndg/soap/utils/etree.py
ndg_saml.egg-info/PKG-INFO
ndg_saml.egg-info/SOURCES.txt
ndg_saml.egg-info/dependency_links.txt
ndg_saml.egg-info/entry_points.txt
ndg_saml.egg-info/namespace_packages.txt
ndg_saml.egg-info/not-zip-safe
ndg_saml.egg-info/requires.txt
ndg_saml.egg-info/top_level.txt